Metadata-Version: 2.1
Name: marius-lib
Version: 0.1
Summary: This is a test project
Home-page: https://google.com
Author: eu
Author-email: eu@toteu.com
License: UNKNOWN
Platform: UNKNOWN
Requires-Python: >=3.10
